[
  {
    "id": 1,
    "name": "session_start",
    "type": "sessionEvent",
    "version": "4.0",
    "deviceType": "Galaxy 10",
    "deviceFamily": "Galaxy",
    "os": "Android",
    "country": "USA",
    "city": "NYC",
    "carrier": "Verizon"
  },
  {
    "id": 2,
    "name": "session_end",
    "type": "sessionEvent",
    "version": "1.0",
    "deviceType": "IPhone x",
    "deviceFamily": "IPhone",
    "os": "iOS",
    "country": "USA",
    "city": "San Francisco",
    "carrier": "T-Mobile"
  },
  {
    "id": 3,
    "name": "ads_click",
    "type": "clickEvent",
    "version": "3.5",
    "deviceType": "Galaxy 7",
    "deviceFamily": "Samsung Galaxy",
    "os": "Android",
    "country": "USA",
    "city": "LA",
    "carrier": "Verizon"
  },
  {
    "id": 4,
    "name": "iap_purchase",
    "type": "iapEvent",
    "version": "2.2",
    "deviceType": "Google Pixel 3",
    "deviceFamily": "Google Pixel",
    "os": "Android",
    "country": "USA",
    "city": "Chicago",
    "carrier": "AT&T"
  },
  {
    "id": 4,
    "name": "video_started",
    "type": "videoEvent",
    "version": "3.8",
    "deviceType": "Google Pixel 3",
    "deviceFamily": "Google Pixel",
    "os": "Android",
    "country": "USA",
    "city": "Denver",
    "carrier": "Sprint"
  }
]